Workbook
Name CONFIG_TAKE_RATE: 'Config'!$B$10
Name CONFIG_DIAMOND_RATE: 'Config'!$B$11
Name CONFIG_RENT: 'Config'!$B$12
Name CONFIG_UTILITY: 'Config'!$B$13
Name CONFIG_BUFFER: 'Config'!$B$14
Name CONFIG_INITIAL_INVEST: 'Config'!$B$15
Name CONFIG_CREATOR_BASE: 'Config'!$B$16
Name CONFIG_CREATOR_REVSHARE: 'Config'!$B$17
Name CONFIG_STAGE_BE: 'Config'!$B$22
Name CONFIG_STAGE_STB: 'Config'!$B$23
Name CONFIG_STAGE_OPT: 'Config'!$B$24

Sheet Config
A1: ⚙️ CONFIG — Single source of truth for all assumptions
A3: TEAM REGISTRY
A4: Team ID | B4: Team Name | C4: Market | D4: Launch Date | E4: Status
A5: COL01 | B5: Team 1 | C5: Colombia | D5: 2025-09-01 | E5: Active
A6: COL02 | B6: Team 2 | C6: Colombia | D6: 2026-02-01 | E6: Active
A9: UE ASSUMPTIONS (edit yellow cells → all sheets update automatically)
A10: Take Rate | B10: 0.65 | C10: ← Named range: CONFIG_TAKE_RATE
A11: Diamond → USD rate | B11: 0.01 | C11: ← Named range: CONFIG_DIAMOND_RATE
A12: Monthly Rent (USD) | B12: 600 | C12: ← Named range: CONFIG_RENT
A13: Monthly Utility (USD) | B13: 800 | C13: ← Named range: CONFIG_UTILITY
A14: Monthly Buffer (USD) | B14: 1000 | C14: ← Named range: CONFIG_BUFFER
A15: Initial Investment/team | B15: 11430 | C15: ← Named range: CONFIG_INITIAL_INVEST
A16: Creator Base Salary | B16: 500 | C16: ← Named range: CONFIG_CREATOR_BASE
A17: Revenue Share % | B17: 0.25 | C17: ← Named range: CONFIG_CREATOR_REVSHARE
A19: STAGE THRESHOLDS (diamonds / month)
A20: Stage | B20: Min Diamonds (≥)
A21: 🌱 Incubation | B21: 0
A22: ⚠️ Breakeven | B22: 500000
A23: ✅ Stable | B23: 1060000
A24: 🚀 Optimistic | B24: 2000000
A26: LEGEND
B27: Yellow = Data entry required
B28: Blue = Actual override (blank → use Config assumption)
B29: Grey = Auto-calculated — do not edit

Sheet Staff
A1: 👥 STAFF — Mark "✓" in team columns; cost allocation auto-calculates
A2: Allocation Coeff = 1 ÷ Teams Covered. Per-team cost = Salary × Coeff (if assigned).
A3: Staff Name | B3: Role | C3: Salary (USD) | D3: COL01 | E3: COL02 | F3: Teams Covered | G3: Alloc Coeff | H3: COL01 Cost (USD) | I3: COL02 Cost (USD)
A4: Ops Manager | B4: Operations | C4: 800 | D4: ✓ | E4: ✓ | F4: =COUNTIF(D4:E4,"✓") | G4: =IF(F4=0,0,1/F4) | H4: =IF(D4="✓",C4*G4,0) | I4: =IF(E4="✓",C4*G4,0)
A5: Dance Teacher | B5: Dance Teacher | C5: 600 | D5: ✓ | F5: =COUNTIF(D5:E5,"✓") | G5: =IF(F5=0,0,1/F5) | H5: =IF(D5="✓",C5*G5,0) | I5: =IF(E5="✓",C5*G5,0)
A6: MUA | B6: MUA | C6: 500 | D6: ✓ | E6: ✓ | F6: =COUNTIF(D6:E6,"✓") | G6: =IF(F6=0,0,1/F6) | H6: =IF(D6="✓",C6*G6,0) | I6: =IF(E6="✓",C6*G6,0)
A7: Tech Support | B7: Tech | C7: 400 | D7: ✓ | E7: ✓ | F7: =COUNTIF(D7:E7,"✓") | G7: =IF(F7=0,0,1/F7) | H7: =IF(D7="✓",C7*G7,0) | I7: =IF(E7="✓",C7*G7,0)
A8: TOTAL | C8: =SUM(C4:C7) | H8: =SUM(H4:H7) | I8: =SUM(I4:I7)

Sheet Monthly_Data
A1: 📋 MONTHLY DATA — Enter actual values (blue = override; blank = use Config default)
B2: ── COL01 ── | I2: ── COL02 ── | P2: ── SHARED ADMIN (split equally across teams) ──
A3: Month | B3: Diamonds | C3: Creators | D3: Creator Sal. Actual | E3: Rent Actual | F3: Utility Actual | G3: Buffer Actual | H3: Other Cost Actual | I3: Diamonds | J3: Creators | K3: Creator Sal. Actual | L3: Rent Actual | M3: Utility Actual | N3: Buffer Actual | O3: Other Cost Actual | P3: Clothes | Q3: Taxi | R3: Meals | S3: Other Admin
A4: 2026-02 | B4: 890000 | C4: 4 | I4: 450000 | J4: 3
A5: 2026-03 | B5: 1200000 | C5: 4 | I5: 620000 | J5: 3

Sheet UE_Summary
A1: 📊 UE SUMMARY — Auto-calculated. Do not edit.
A2: Month | B2: Team ID | C2: Team Name | D2: Diamonds | E2: Revenue (USD) | F2: Creator Salary | G2: Staff Cost | H2: Rent | I2: Utility | J2: Buffer | K2: Admin Share | L2: Other | M2: Total Cost | N2: Gross Profit | O2: Margin % | P2: Stage | Q2: Cumul. Net | R2: Initial Invest. | S2: Recovered? | T2: Month #
A3: 2026-02 | B3: COL01 | C3: Team 1 | D3: =IF(Monthly_Data!B4="",0,Monthly_Data!B4) | E3: =IF(Monthly_Data!B4="",0,Monthly_Data!B4*CONFIG_DIAMOND_RATE*CONFIG_TAKE_RATE) | F3: =IF(Monthly_Data!D4<>"",Monthly_Data!D4,MAX(CONFIG_CREATOR_BASE*IF(Monthly_Data!C4="",0,Monthly_Data!C4),Monthly_Data!B4*CONFIG_DIAMOND_RATE*CONFIG_TAKE_RATE*CONFIG_CREATOR_REVSHARE)) | G3: =SUM(Staff!H4:Staff!H200) | H3: =IF(Monthly_Data!E4<>"",Monthly_Data!E4,CONFIG_RENT) | I3: =IF(Monthly_Data!F4<>"",Monthly_Data!F4,CONFIG_UTILITY) | J3: =IF(Monthly_Data!G4<>"",Monthly_Data!G4,CONFIG_BUFFER) | K3: =SUM(Monthly_Data!P4:S4)/2 | L3: =IF(Monthly_Data!H4<>"",Monthly_Data!H4,0) | M3: =SUM(F3:L3) | N3: =E3-M3 | O3: =IF(E3=0,0,N3/E3) | P3: =IFS(D3>=CONFIG_STAGE_OPT,"🚀 Optimistic",D3>=CONFIG_STAGE_STB,"✅ Stable",D3>=CONFIG_STAGE_BE,"⚠️ Breakeven",TRUE,"🌱 Incubation") | Q3: =N3 | R3: =CONFIG_INITIAL_INVEST | S3: =IF(Q3>=CONFIG_INITIAL_INVEST,"✅ YES","⏳ No") | T3: =DATEDIF(DATE(LEFT('Config'!$D$5,4),MID('Config'!$D$5,6,2),1),DATE(LEFT(A3,4),RIGHT(A3,2),1),"M")+1
A4: 2026-02 | B4: COL02 | C4: Team 2 | D4: =IF(Monthly_Data!I4="",0,Monthly_Data!I4) | E4: =IF(Monthly_Data!I4="",0,Monthly_Data!I4*CONFIG_DIAMOND_RATE*CONFIG_TAKE_RATE) | F4: =IF(Monthly_Data!K4<>"",Monthly_Data!K4,MAX(CONFIG_CREATOR_BASE*IF(Monthly_Data!J4="",0,Monthly_Data!J4),Monthly_Data!I4*CONFIG_DIAMOND_RATE*CONFIG_TAKE_RATE*CONFIG_CREATOR_REVSHARE)) | G4: =SUM(Staff!I4:Staff!I200) | H4: =IF(Monthly_Data!L4<>"",Monthly_Data!L4,CONFIG_RENT) | I4: =IF(Monthly_Data!M4<>"",Monthly_Data!M4,CONFIG_UTILITY) | J4: =IF(Monthly_Data!N4<>"",Monthly_Data!N4,CONFIG_BUFFER) | K4: =SUM(Monthly_Data!P4:S4)/2 | L4: =IF(Monthly_Data!O4<>"",Monthly_Data!O4,0) | M4: =SUM(F4:L4) | N4: =E4-M4 | O4: =IF(E4=0,0,N4/E4) | P4: =IFS(D4>=CONFIG_STAGE_OPT,"🚀 Optimistic",D4>=CONFIG_STAGE_STB,"✅ Stable",D4>=CONFIG_STAGE_BE,"⚠️ Breakeven",TRUE,"🌱 Incubation") | Q4: =N4 | R4: =CONFIG_INITIAL_INVEST | S4: =IF(Q4>=CONFIG_INITIAL_INVEST,"✅ YES","⏳ No") | T4: =DATEDIF(DATE(LEFT('Config'!$D$6,4),MID('Config'!$D$6,6,2),1),DATE(LEFT(A4,4),RIGHT(A4,2),1),"M")+1
A5: 2026-03 | B5: COL01 | C5: Team 1 | D5: =IF(Monthly_Data!B5="",0,Monthly_Data!B5) | E5: =IF(Monthly_Data!B5="",0,Monthly_Data!B5*CONFIG_DIAMOND_RATE*CONFIG_TAKE_RATE) | F5: =IF(Monthly_Data!D5<>"",Monthly_Data!D5,MAX(CONFIG_CREATOR_BASE*IF(Monthly_Data!C5="",0,Monthly_Data!C5),Monthly_Data!B5*CONFIG_DIAMOND_RATE*CONFIG_TAKE_RATE*CONFIG_CREATOR_REVSHARE)) | G5: =SUM(Staff!H4:Staff!H200) | H5: =IF(Monthly_Data!E5<>"",Monthly_Data!E5,CONFIG_RENT) | I5: =IF(Monthly_Data!F5<>"",Monthly_Data!F5,CONFIG_UTILITY) | J5: =IF(Monthly_Data!G5<>"",Monthly_Data!G5,CONFIG_BUFFER) | K5: =SUM(Monthly_Data!P5:S5)/2 | L5: =IF(Monthly_Data!H5<>"",Monthly_Data!H5,0) | M5: =SUM(F5:L5) | N5: =E5-M5 | O5: =IF(E5=0,0,N5/E5) | P5: =IFS(D5>=CONFIG_STAGE_OPT,"🚀 Optimistic",D5>=CONFIG_STAGE_STB,"✅ Stable",D5>=CONFIG_STAGE_BE,"⚠️ Breakeven",TRUE,"🌱 Incubation") | Q5: =N5+N3 | R5: =CONFIG_INITIAL_INVEST | S5: =IF(Q5>=CONFIG_INITIAL_INVEST,"✅ YES","⏳ No") | T5: =DATEDIF(DATE(LEFT('Config'!$D$5,4),MID('Config'!$D$5,6,2),1),DATE(LEFT(A5,4),RIGHT(A5,2),1),"M")+1
A6: 2026-03 | B6: COL02 | C6: Team 2 | D6: =IF(Monthly_Data!I5="",0,Monthly_Data!I5) | E6: =IF(Monthly_Data!I5="",0,Monthly_Data!I5*CONFIG_DIAMOND_RATE*CONFIG_TAKE_RATE) | F6: =IF(Monthly_Data!K5<>"",Monthly_Data!K5,MAX(CONFIG_CREATOR_BASE*IF(Monthly_Data!J5="",0,Monthly_Data!J5),Monthly_Data!I5*CONFIG_DIAMOND_RATE*CONFIG_TAKE_RATE*CONFIG_CREATOR_REVSHARE)) | G6: =SUM(Staff!I4:Staff!I200) | H6: =IF(Monthly_Data!L5<>"",Monthly_Data!L5,CONFIG_RENT) | I6: =IF(Monthly_Data!M5<>"",Monthly_Data!M5,CONFIG_UTILITY) | J6: =IF(Monthly_Data!N5<>"",Monthly_Data!N5,CONFIG_BUFFER) | K6: =SUM(Monthly_Data!P5:S5)/2 | L6: =IF(Monthly_Data!O5<>"",Monthly_Data!O5,0) | M6: =SUM(F6:L6) | N6: =E6-M6 | O6: =IF(E6=0,0,N6/E6) | P6: =IFS(D6>=CONFIG_STAGE_OPT,"🚀 Optimistic",D6>=CONFIG_STAGE_STB,"✅ Stable",D6>=CONFIG_STAGE_BE,"⚠️ Breakeven",TRUE,"🌱 Incubation") | Q6: =N6+N4 | R6: =CONFIG_INITIAL_INVEST | S6: =IF(Q6>=CONFIG_INITIAL_INVEST,"✅ YES","⏳ No") | T6: =DATEDIF(DATE(LEFT('Config'!$D$6,4),MID('Config'!$D$6,6,2),1),DATE(LEFT(A6,4),RIGHT(A6,2),1),"M")+1

Sheet Team_COL01
A1: 🏠 COL01 — Team 1 (Colombia)
A2: Launch Date: | B2: 2025-09-01 | C2: Status: | D2: Active | E2: Market: | F2: Colombia
A4: Month | B4: Diamonds | C4: Revenue | D4: Creator Sal. | E4: Staff Cost | F4: Rent | G4: Utility | H4: Buffer | I4: Admin | J4: Other | K4: Total Cost | L4: Gross Profit | M4: Margin % | N4: Stage | O4: Cumul. Net | P4: Initial Invest. | Q4: Recovered? | R4: Month #
A5: =UE_Summary!A3 | B5: =UE_Summary!D3 | C5: =UE_Summary!E3 | D5: =UE_Summary!F3 | E5: =UE_Summary!G3 | F5: =UE_Summary!H3 | G5: =UE_Summary!I3 | H5: =UE_Summary!J3 | I5: =UE_Summary!K3 | ... R5: =UE_Summary!T3
A6: =UE_Summary!A5 | B6: =UE_Summary!D5 | C6: =UE_Summary!E5 | D6: =UE_Summary!F5 | E6: =UE_Summary!G5 | F6: =UE_Summary!H5 | G6: =UE_Summary!I5 | H6: =UE_Summary!J5 | I6: =UE_Summary!K5 | ... R6: =UE_Summary!T5

Sheet Team_COL02
A1: 🏠 COL02 — Team 2 (Colombia)
A2: Launch Date: | B2: 2026-02-01 | C2: Status: | D2: Active | E2: Market: | F2: Colombia
A4: Month | B4: Diamonds | C4: Revenue | D4: Creator Sal. | E4: Staff Cost | F4: Rent | G4: Utility | H4: Buffer | I4: Admin | J4: Other | K4: Total Cost | L4: Gross Profit | M4: Margin % | N4: Stage | O4: Cumul. Net | P4: Initial Invest. | Q4: Recovered? | R4: Month #
A5: =UE_Summary!A4 | B5: =UE_Summary!D4 | C5: =UE_Summary!E4 | D5: =UE_Summary!F4 | E5: =UE_Summary!G4 | F5: =UE_Summary!H4 | G5: =UE_Summary!I4 | H5: =UE_Summary!J4 | I5: =UE_Summary!K4 | ... R5: =UE_Summary!T4
A6: =UE_Summary!A6 | B6: =UE_Summary!D6 | C6: =UE_Summary!E6 | D6: =UE_Summary!F6 | E6: =UE_Summary!G6 | F6: =UE_Summary!H6 | G6: =UE_Summary!I6 | H6: =UE_Summary!J6 | I6: =UE_Summary!K6 | ... R6: =UE_Summary!T6
